{
   "gallery": {
      "galleryhead": "Fans gather to celebrate Super Bowl victory at Eagles Parade",
      "gallerydate": "02/08/2018",
      "galleryyear": "2018",
      "galleryid": "473349183",
      "comscorekw": "pageview_candidate",
      "omday": "Thursday",
      "omtime": "4:00PM",
      "omdaytype": "Weekday",
      "photo": [
         {
            "caption": "Eagles' Jason Kelce was fired-up during his speech at the Eagles Super Bowl Champions celebration at the Art Museum in Philadelphia on February 8, 2018.",
            "title": "PARADE09-K",
            "photoCredit": "DAVID MAIALETTI / Staff Photographer",
            "slideNumber": "photo 1 - 473349183 - PARADE09-K - DAVID MAIALETTI / Staff Photographer",
            "emailThis": "http://www.philly.com/philly/super-bowl-lii/fans-gather-to-celebrate-super-bowl-victory-at-eagles-parade-20180208.html#photoNumber=0",
            "photoWidth": "2600",
            "photoHeight": "1733",
            "reprint": "true",
            "_name": "http://media.philly.com/images/600*450/RS_galleryImages_x_20180208_PARADE09_K.JPG"
         },
         {
            "caption": "Fireworks fly above the Philadelphia Museum of Art during the Eagles Super Bowl LII victory celebration at on Thursday, February 8, 2018.",
            "title": "PARADE09",
            "photoCredit": "YONG KIM / Staff Photographer",
            "slideNumber": "photo 2 - 473349183 - PARADE09 - YONG KIM / Staff Photographer",
            "emailThis": "http://www.philly.com/philly/super-bowl-lii/fans-gather-to-celebrate-super-bowl-victory-at-eagles-parade-20180208.html#photoNumber=1",
            "photoWidth": "2400",
            "photoHeight": "1479",
            "reprint": "true",
            "_name": "http://media.philly.com/images/600*450/RS_galleryImages_x_20180208_PARADE09_15.JPG"
         },
         {
            "caption": "With City Hall in the background Eagle Super Bowl MVP Nick Foles, left, passes the Vince Lombardi Trophy to Eagle quarterback Carson Wentz, right, to hold up during that part of the parade, while backup quarterback Nate Sudfeld, center, reaches over them both to take a photo of the huge crowd. Eagle owner Jeffrey Lurie, extreme left, takes it all in during the Eagles Super bowl Parade on Thursday February 8, 2018.",
            "title": "020818_qbsandlombardi_1200",
            "photoCredit": "MICHAEL BRYANT / Staff Photographer",
            "slideNumber": "photo 3 - 473349183 - 020818_qbsandlombardi_1200 - MICHAEL BRYANT / Staff Photographer",
            "emailThis": "http://www.philly.com/philly/super-bowl-lii/fans-gather-to-celebrate-super-bowl-victory-at-eagles-parade-20180208.html#photoNumber=2",
            "photoWidth": "1200",
            "photoHeight": "800",
            "reprint": "true",
            "_name": "http://media.philly.com/images/600*450/RS_galleryImages_1200x800_020818_qbsandlombardi_1200.jpg"
         },
         {
            "caption": "Eagle players Beau Allen and Chris Long (right) show their appreciation to their fans while riding atop a bus near City Hall during the Eagles Super Bowl Parade.",
            "title": "ssParade09-b17",
            "photoCredit": "MICHAEL BRYANT / Staff Photographer",
            "slideNumber": "photo 4 - 473349183 - ssParade09-b17 - MICHAEL BRYANT / Staff Photographer",
            "emailThis": "http://www.philly.com/philly/super-bowl-lii/fans-gather-to-celebrate-super-bowl-victory-at-eagles-parade-20180208.html#photoNumber=3",
            "photoWidth": "2048",
            "photoHeight": "1365",
            "reprint": "true",
            "_name": "http://media.philly.com/images/600*450/ssParade09-b17.JPG"
         },
         {
            "caption": "Philadelphia Eagles parade down Broad street during the Super Bowl Champions parade in South Philadelphia. Thursday, February 8, 2018.",
            "title": "PARADE09-S",
            "photoCredit": "JOSE F. MORENO / Staff Photographer",
            "slideNumber": "photo 5 - 473349183 - PARADE09-S - JOSE F. MORENO / Staff Photographer",
            "emailThis": "http://www.philly.com/philly/super-bowl-lii/fans-gather-to-celebrate-super-bowl-victory-at-eagles-parade-20180208.html#photoNumber=4",
            "photoWidth": "3334",
            "photoHeight": "2223",
            "reprint": "true",
            "_name": "http://media.philly.com/images/600*450/RS_galleryImages_x_20180208_PARADE09_S.jpg"
         },
         {
            "caption": "South Broad St. at Lombard is lined with fans as the Super Bowl winning Philadelphia Eagles motorcade makes its way north from the stadium area during the Super Bowl Champions parade.",
            "title": "ssParade09-b16",
            "photoCredit": "DAVID SWANSON / Staff Photographer",
            "slideNumber": "photo 6 - 473349183 - ssParade09-b16 - DAVID SWANSON / Staff Photographer",
            "emailThis": "http://www.philly.com/philly/super-bowl-lii/fans-gather-to-celebrate-super-bowl-victory-at-eagles-parade-20180208.html#photoNumber=5",
            "photoWidth": "2048",
            "photoHeight": "1365",
            "reprint": "true",
            "_name": "http://media.philly.com/images/600*450/ssParade09-b16.JPG"
         },
         {
            "caption": "Jalen Mills, cornerback with Philadelphia Eagles greets the crowd along S. Broad St. during Super Bowl Champions Parade on Thursday, February 8, 2018. STEVEN M. FALK / Staff Photographer",
            "title": "ssParade09-a696",
            "photoCredit": "STEVEN M. FALK / Staff Photographer",
            "slideNumber": "photo 7 - 473349183 - ssParade09-a696 - STEVEN M. FALK / Staff Photographer",
            "emailThis": "http://www.philly.com/philly/super-bowl-lii/fans-gather-to-celebrate-super-bowl-victory-at-eagles-parade-20180208.html#photoNumber=6",
            "photoWidth": "2048",
            "photoHeight": "1364",
            "reprint": "true",
            "_name": "http://media.philly.com/images/600*450/RS_galleryImages_x_20180208_ssParade09_a696_455111397.JPG"
         },
         {
            "caption": "The Washington Monument in Eakins Oval is pictured amid smoke from fireworks during the Eagles' Super Bowl ceremony on Thursday, Feb. 8, 2018.",
            "title": "ssParade09-b18",
            "photoCredit": "TIM TAI / Staff Photographer",
            "slideNumber": "photo 8 - 473349183 - ssParade09-b18 - TIM TAI / Staff Photographer",
            "emailThis": "http://www.philly.com/philly/super-bowl-lii/fans-gather-to-celebrate-super-bowl-victory-at-eagles-parade-20180208.html#photoNumber=7",
            "photoWidth": "2048",
            "photoHeight": "1365",
            "reprint": "true",
            "_name": "http://media.philly.com/images/600*450/ssParade09-b18.JPG"
         },
         {
            "caption": "Willie Cook hawks Philadelphia Inquirer newspapers during the Eagles' Super Bowl parade on Thursday, Feb. 8, 2018.",
            "title": "ssParade09-b15",
            "photoCredit": "TIM TAI / Staff Photographer",
            "slideNumber": "photo 9 - 473349183 - ssParade09-b15 - TIM TAI / Staff Photographer",
            "emailThis": "http://www.philly.com/philly/super-bowl-lii/fans-gather-to-celebrate-super-bowl-victory-at-eagles-parade-20180208.html#photoNumber=8",
            "photoWidth": "2048",
            "photoHeight": "1365",
            "reprint": "true",
            "_name": "http://media.philly.com/images/600*450/ssParade09-b15.JPG"
         },
         {
            "caption": "A sea of Eagles fans stand shoulder to shoulder along N. 15th St. as seen from Cherry St. on Thursday, February 8, 2018. Fans came out to cheer their Super Bowl winning team.",
            "title": "ssParade09-b13",
            "photoCredit": "TIM TAI / Staff Photographer",
            "slideNumber": "photo 10 - 473349183 - ssParade09-b13 - TIM TAI / Staff Photographer",
            "emailThis": "http://www.philly.com/philly/super-bowl-lii/fans-gather-to-celebrate-super-bowl-victory-at-eagles-parade-20180208.html#photoNumber=9",
            "photoWidth": "2048",
            "photoHeight": "1365",
            "reprint": "true",
            "_name": "http://media.philly.com/images/600*450/ssParade09-b13.JPG"
         },
         {
            "caption": "Defensive tackle Fletcher Cox hoists the Vince Lombardi Trophy during the Super Bowl Champions parade up S. Broad St. on Thursday, February 8, 2018.",
            "title": "ssParade09-a591",
            "photoCredit": "STEVEN M. FALK / Staff Photographer",
            "slideNumber": "photo 11 - 473349183 - ssParade09-a591 - STEVEN M. FALK / Staff Photographer",
            "emailThis": "http://www.philly.com/philly/super-bowl-lii/fans-gather-to-celebrate-super-bowl-victory-at-eagles-parade-20180208.html#photoNumber=10",
            "photoWidth": "2048",
            "photoHeight": "1364",
            "reprint": "true",
            "_name": "http://media.philly.com/images/600*450/RS_galleryImages_x_20180208_ssParade09_a591_455235432.JPG"
         },
         {
            "caption": "Philadelphia police motorcycle unit escort the procession of Eagles players and cheerleaders up S. Broad St. during the Super Bowl Champions parade through the city on Thursday, February 8, 2018. STEVEN M. FALK / Staff Photographer",
            "title": "ssParade09-a381",
            "photoCredit": "STEVEN M. FALK / Staff Photographer",
            "slideNumber": "photo 12 - 473349183 - ssParade09-a381 - STEVEN M. FALK / Staff Photographer",
            "emailThis": "http://www.philly.com/philly/super-bowl-lii/fans-gather-to-celebrate-super-bowl-victory-at-eagles-parade-20180208.html#photoNumber=11",
            "photoWidth": "2048",
            "photoHeight": "1365",
            "reprint": "true",
            "_name": "http://media.philly.com/images/600*450/ssParade09-a381.JPG"
         },
         {
            "caption": "Buses holding players, coaches and team staff reach the Philadelphia Museum of Art during the Eagles' Super Bowl parade on Thursday, Feb. 8, 2018.",
            "title": "PARADE09-t",
            "photoCredit": "TIM TAI / Staff Photographer",
            "slideNumber": "photo 13 - 473349183 - PARADE09-t - TIM TAI / Staff Photographer",
            "emailThis": "http://www.philly.com/philly/super-bowl-lii/fans-gather-to-celebrate-super-bowl-victory-at-eagles-parade-20180208.html#photoNumber=12",
            "photoWidth": "2400",
            "photoHeight": "1600",
            "reprint": "true",
            "_name": "http://media.philly.com/images/600*450/RS_galleryImages_x_20180208_PARADE09_t_455108384.jpg"
         },
         {
            "caption": "Thousands watch the Super Bowl LII champion Philadelphia Eagles Parade Thursday February 8, 2018",
            "title": "PPARADE09-m",
            "photoCredit": "DAVID SWANSON / Staff Photographer",
            "slideNumber": "photo 14 - 473349183 - PPARADE09-m - DAVID SWANSON / Staff Photographer",
            "emailThis": "http://www.philly.com/philly/super-bowl-lii/fans-gather-to-celebrate-super-bowl-victory-at-eagles-parade-20180208.html#photoNumber=13",
            "photoWidth": "3429",
            "photoHeight": "5144",
            "reprint": "true",
            "_name": "http://media.philly.com/images/600*450/RS_galleryImages_x_20180208_PPARADE09_m_455306563.JPG"
         },
         {
            "caption": "Thousands watch the Super Bowl LII champion Philadelphia Eagles Parade Thursday February 8,",
            "title": "PPARADE09-o",
            "photoCredit": "DAVID SWANSON / Staff Photographer",
            "slideNumber": "photo 15 - 473349183 - PPARADE09-o - DAVID SWANSON / Staff Photographer",
            "emailThis": "http://www.philly.com/philly/super-bowl-lii/fans-gather-to-celebrate-super-bowl-victory-at-eagles-parade-20180208.html#photoNumber=14",
            "photoWidth": "1080",
            "photoHeight": "720",
            "reprint": "true",
            "_name": "http://media.philly.com/images/600*450/RS_galleryImages_x_20180208_PPARADE09_oo_455162011.jpg"
         },
         {
            "caption": "Eagles fan Ada Tate 28, from Overbrook section Philadelphia screams as thousands walk west on Market street towards 30th street Station after the Eagles Parade, Thursday, Feb. 8, 2018.",
            "title": "ssParade09-b3",
            "photoCredit": "STEVEN M. FALK / Staff Photograp",
            "slideNumber": "photo 16 - 473349183 - ssParade09-b3 - STEVEN M. FALK / Staff Photograp",
            "emailThis": "http://www.philly.com/philly/super-bowl-lii/fans-gather-to-celebrate-super-bowl-victory-at-eagles-parade-20180208.html#photoNumber=15",
            "photoWidth": "2048",
            "photoHeight": "1431",
            "reprint": "true",
            "_name": "http://media.philly.com/images/600*450/ssParade09-b3.JPG"
         },
         {
            "caption": "Eagles fan Reggie Hylick, waves his eagles flag, hours before the start of the Eagles Super Bowl Champions parade on Broad St. in South Philadelphia. Thursday, February 8, 2018.",
            "title": "PARADE09-G",
            "photoCredit": "JOSE F. MORENO / Staff Photographer",
            "slideNumber": "photo 17 - 473349183 - PARADE09-G - JOSE F. MORENO / Staff Photographer",
            "emailThis": "http://www.philly.com/philly/super-bowl-lii/fans-gather-to-celebrate-super-bowl-victory-at-eagles-parade-20180208.html#photoNumber=16",
            "photoWidth": "2588",
            "photoHeight": "1725",
            "reprint": "true",
            "_name": "http://media.philly.com/images/600*450/RS_galleryImages_x_20180208_PARADE09_G.jpg"
         },
         {
            "caption": "Philadelphia Eagles fans take photos with heir cell phones during the Super Bowl Champions parade in South Philadelphia. Thursday, February 8, 2018.",
            "title": "PARADE09-P",
            "photoCredit": "JOSE F. MORENO / Staff Photographer",
            "slideNumber": "photo 18 - 473349183 - PARADE09-P - JOSE F. MORENO / Staff Photographer",
            "emailThis": "http://www.philly.com/philly/super-bowl-lii/fans-gather-to-celebrate-super-bowl-victory-at-eagles-parade-20180208.html#photoNumber=17",
            "photoWidth": "2529",
            "photoHeight": "1687",
            "reprint": "true",
            "_name": "http://media.philly.com/images/600*450/RS_galleryImages_x_20180208_PARADE09_P.jpg"
         },
         {
            "caption": "The crowd cheers as the Eagles' Super Bowl parade passes them on Thursday, Feb. 8, 2018.",
            "title": "PARADE09-aa",
            "photoCredit": "TIM TAI / Staff Photographer",
            "slideNumber": "photo 19 - 473349183 - PARADE09-aa - TIM TAI / Staff Photographer",
            "emailThis": "http://www.philly.com/philly/super-bowl-lii/fans-gather-to-celebrate-super-bowl-victory-at-eagles-parade-20180208.html#photoNumber=18",
            "photoWidth": "2400",
            "photoHeight": "1600",
            "reprint": "true",
            "_name": "http://media.philly.com/images/600*450/RS_galleryImages_x_20180208_PARADE09_aa_455127470.jpg"
         },
         {
            "caption": "Thousands watch the Super Bowl LII champion Philadelphia Eagles Parade, Thursday February 8, 2018.",
            "title": "PPARADE09-g",
            "photoCredit": "DAVID SWANSON / Staff Photographer",
            "slideNumber": "photo 20 - 473349183 - PPARADE09-g - DAVID SWANSON / Staff Photographer",
            "emailThis": "http://www.philly.com/philly/super-bowl-lii/fans-gather-to-celebrate-super-bowl-victory-at-eagles-parade-20180208.html#photoNumber=19",
            "photoWidth": "3000",
            "photoHeight": "2000",
            "reprint": "true",
            "_name": "http://media.philly.com/images/600*450/RS_galleryImages_x_20180208_PPARADE09_g_455248308.JPG"
         },
         {
            "caption": "Thousands watch the Super Bowl LII champion Philadelphia Eagles Parade Thursday February 8, 2018.",
            "title": "PPARADE09-f",
            "photoCredit": "DAVID SWANSON / Staff Photographer",
            "slideNumber": "photo 21 - 473349183 - PPARADE09-f - DAVID SWANSON / Staff Photographer",
            "emailThis": "http://www.philly.com/philly/super-bowl-lii/fans-gather-to-celebrate-super-bowl-victory-at-eagles-parade-20180208.html#photoNumber=20",
            "photoWidth": "5144",
            "photoHeight": "3429",
            "reprint": "true",
            "_name": "http://media.philly.com/images/600*450/RS_galleryImages_x_20180208_PPARADE09_f_455285809.JPG"
         },
         {
            "caption": "Philadelphia Eagles head coach Doug Pederson, right, and executive VP Howie Roseman walk along the parade route with the Lombardi trophy during the Super Bowl LII victory parade, Thursday, Feb 8, 2018, in Philadelphia.",
            "title": "ssParade09-a41",
            "photoCredit": "AP Photo / Michael Perez",
            "slideNumber": "photo 22 - 473349183 - ssParade09-a41 - AP Photo / Michael Perez",
            "emailThis": "http://www.philly.com/philly/super-bowl-lii/fans-gather-to-celebrate-super-bowl-victory-at-eagles-parade-20180208.html#photoNumber=21",
            "photoWidth": "2048",
            "photoHeight": "1364",
            "reprint": "true",
            "_name": "http://media.philly.com/images/600*450/ssParade09-a41.JPG"
         },
         {
            "caption": "Thousands watch the Super Bowl LII champion Philadelphia Eagles Parade Thursday February 8, 2018.",
            "title": "PPARADE09-a",
            "photoCredit": "DAVID SWANSON / Staff Photographer",
            "slideNumber": "photo 23 - 473349183 - PPARADE09-a - DAVID SWANSON / Staff Photographer",
            "emailThis": "http://www.philly.com/philly/super-bowl-lii/fans-gather-to-celebrate-super-bowl-victory-at-eagles-parade-20180208.html#photoNumber=22",
            "photoWidth": "5144",
            "photoHeight": "3429",
            "reprint": "true",
            "_name": "http://media.philly.com/images/600*450/RS_galleryImages_x_20180208_PPARADE09_a_455323146.JPG"
         },
         {
            "caption": "Buses holding players, coaches and team staff reach the Philadelphia Museum of Art during the Eagles' Super Bowl parade on Thursday, Feb. 8, 2018.",
            "title": "PARADE09-bb",
            "photoCredit": "TIM TAI / Staff Photographer",
            "slideNumber": "photo 24 - 473349183 - PARADE09-bb - TIM TAI / Staff Photographer",
            "emailThis": "http://www.philly.com/philly/super-bowl-lii/fans-gather-to-celebrate-super-bowl-victory-at-eagles-parade-20180208.html#photoNumber=23",
            "photoWidth": "2400",
            "photoHeight": "1600",
            "reprint": "true",
            "_name": "http://media.philly.com/images/600*450/RS_galleryImages_x_20180208_PARADE09_bb_455308822.jpg"
         },
         {
            "caption": "Philadelphia Eagles fans gather in S. Philadelphia for the Super Bowl Champions parade up S. Broad St. to Philadelphia Art Museum on Thursday, February 8, 2018.",
            "title": "ssParade09-a256",
            "photoCredit": "STEVEN M. FALK / Staff Photographer",
            "slideNumber": "photo 25 - 473349183 - ssParade09-a256 - STEVEN M. FALK / Staff Photographer",
            "emailThis": "http://www.philly.com/philly/super-bowl-lii/fans-gather-to-celebrate-super-bowl-victory-at-eagles-parade-20180208.html#photoNumber=24",
            "photoWidth": "2048",
            "photoHeight": "1364",
            "reprint": "true",
            "_name": "http://media.philly.com/images/600*450/RS_galleryImages_x_20180208_ssParade09_a256_455228607.JPG"
         },
         {
            "caption": "Philadelphia Eagles NFL football team mascot Swoop waves during the Super Bowl LII victory parade, Thursday, Feb 8, 2018, in Philadelphia.",
            "title": "ssParade09-a42",
            "photoCredit": "AP Photo / Michael Perezr",
            "slideNumber": "photo 26 - 473349183 - ssParade09-a42 - AP Photo / Michael Perezr",
            "emailThis": "http://www.philly.com/philly/super-bowl-lii/fans-gather-to-celebrate-super-bowl-victory-at-eagles-parade-20180208.html#photoNumber=25",
            "photoWidth": "2048",
            "photoHeight": "1364",
            "reprint": "true",
            "_name": "http://media.philly.com/images/600*450/ssParade09-a42.JPG"
         },
         {
            "caption": "Philadelphia Eagles head coach Doug Pederson holds up the Vince Lombardi trophy during the Super Bowl LII victory parade, Thursday, Feb 8, 2018, in Philadelphia.",
            "title": "ssParade09-a40",
            "photoCredit": "AP Photo / Michael Perez",
            "slideNumber": "photo 27 - 473349183 - ssParade09-a40 - AP Photo / Michael Perez",
            "emailThis": "http://www.philly.com/philly/super-bowl-lii/fans-gather-to-celebrate-super-bowl-victory-at-eagles-parade-20180208.html#photoNumber=26",
            "photoWidth": "2048",
            "photoHeight": "1364",
            "reprint": "true",
            "_name": "http://media.philly.com/images/600*450/ssParade09-a40.JPG"
         },
         {
            "caption": "Eagles fan Joseph Carotozzola, walks around before the start of the Eagles Super Bowl Champions parade on Broad St. in South Philadelphia. Thursday, February 8, 2018.",
            "title": "PARADE09-I",
            "photoCredit": "JOSE F. MORENO / Staff Photographer",
            "slideNumber": "photo 28 - 473349183 - PARADE09-I - JOSE F. MORENO / Staff Photographer",
            "emailThis": "http://www.philly.com/philly/super-bowl-lii/fans-gather-to-celebrate-super-bowl-victory-at-eagles-parade-20180208.html#photoNumber=27",
            "photoWidth": "2384",
            "photoHeight": "1589",
            "reprint": "true",
            "_name": "http://media.philly.com/images/600*450/RS_galleryImages_x_20180208_PARADE09_I.jpg"
         },
         {
            "caption": "Eagles fans cheer near Philadelphia City Hall before the start of the Eagles Super Bowl LII victory parade through Center City Philadelphia after starting near the stadium in S. Philadelphia on Thursday, February 8, 2018.",
            "title": "ssParade09-a38",
            "photoCredit": "YONG KIM / Staff Photographer",
            "slideNumber": "photo 29 - 473349183 - ssParade09-a38 - YONG KIM / Staff Photographer",
            "emailThis": "http://www.philly.com/philly/super-bowl-lii/fans-gather-to-celebrate-super-bowl-victory-at-eagles-parade-20180208.html#photoNumber=28",
            "photoWidth": "2048",
            "photoHeight": "1335",
            "reprint": "true",
            "_name": "http://media.philly.com/images/600*450/ssParade09-a38.JPG"
         },
         {
            "caption": "Eagles president Don Smolenski (left) holds up the Lombardi Trophy as the Eagles Super Bowl victory parade passes City Hall February 8, 2018.",
            "title": "PASSES08-D",
            "photoCredit": "TOM GRALISH / Staff Photographer",
            "slideNumber": "photo 30 - 473349183 - PASSES08-D - TOM GRALISH / Staff Photographer",
            "emailThis": "http://www.philly.com/philly/super-bowl-lii/fans-gather-to-celebrate-super-bowl-victory-at-eagles-parade-20180208.html#photoNumber=29",
            "photoWidth": "3708",
            "photoHeight": "2472",
            "reprint": "true",
            "_name": "http://media.philly.com/images/600*450/RS_galleryImages_x_20180208_PARADE09_D_455185101.jpg"
         },
         {
            "caption": "Kevin Edwards, of Bristol PA wears his underdog mask while celebrating the Philadelphia Eagles Super Bowl LII victory in Minneapolis.",
            "title": "ssParade09-a31",
            "photoCredit": "MICHAEL BRYANT / Staff Photographer",
            "slideNumber": "photo 31 - 473349183 - ssParade09-a31 - MICHAEL BRYANT / Staff Photographer",
            "emailThis": "http://www.philly.com/philly/super-bowl-lii/fans-gather-to-celebrate-super-bowl-victory-at-eagles-parade-20180208.html#photoNumber=30",
            "photoWidth": "2048",
            "photoHeight": "1364",
            "reprint": "true",
            "_name": "http://media.philly.com/images/600*450/ssParade09-a31.JPG"
         },
         {
            "caption": "Thousands watch the Super Bowl LII champion Philadelphia Eagles Parade Thursday February 8, 2018",
            "title": "PPARADE09-h",
            "photoCredit": "DAVID SWANSON / Staff Photographer",
            "slideNumber": "photo 32 - 473349183 - PPARADE09-h - DAVID SWANSON / Staff Photographer",
            "emailThis": "http://www.philly.com/philly/super-bowl-lii/fans-gather-to-celebrate-super-bowl-victory-at-eagles-parade-20180208.html#photoNumber=31",
            "photoWidth": "5144",
            "photoHeight": "3429",
            "reprint": "true",
            "_name": "http://media.philly.com/images/600*450/RS_galleryImages_x_20180208_PPARADE09_h_455276242.JPG"
         },
         {
            "caption": "Kevin Ogborn of Washington Crossing, PA walks on stilts and waves an Eagles flag at Dilworth Plaza in Center City before the Eagles' Super Bowl Champions parade on Thursday, Feb. 8, 2018.",
            "title": "ssParade09-a28",
            "photoCredit": "TIM TAI / Staff Photographer",
            "slideNumber": "photo 33 - 473349183 - ssParade09-a28 - TIM TAI / Staff Photographer",
            "emailThis": "http://www.philly.com/philly/super-bowl-lii/fans-gather-to-celebrate-super-bowl-victory-at-eagles-parade-20180208.html#photoNumber=32",
            "photoWidth": "2048",
            "photoHeight": "1364",
            "reprint": "true",
            "_name": "http://media.philly.com/images/600*450/ssParade09-a28.JPG"
         },
         {
            "caption": "Philadelphia Eagles fans gather at the top of S. Broad St. on south side of Philadelphia city hall in anticipation of the start of the Super Bowl Champions parade on Thursday, February 8, 2019.",
            "title": "ssParade09-a25",
            "photoCredit": "YONG KIM / Staff Photographer",
            "slideNumber": "photo 34 - 473349183 - ssParade09-a25 - YONG KIM / Staff Photographer",
            "emailThis": "http://www.philly.com/philly/super-bowl-lii/fans-gather-to-celebrate-super-bowl-victory-at-eagles-parade-20180208.html#photoNumber=33",
            "photoWidth": "2048",
            "photoHeight": "1346",
            "reprint": "true",
            "_name": "http://media.philly.com/images/600*450/ssParade09-a25.JPG"
         },
         {
            "caption": "Philadelphia Eagles fans line the Ben Franklin Parkway on Thursday morning February 8, 2018. The Super Bowl winning team with parade through the streets of Center City starting in S. Philadelphia making its way around City Hall to a platform set up in front of the Art Museum.",
            "title": "ssParade09-a20",
            "photoCredit": "ELIZABETH ROBERTSON / Staff Photographer",
            "slideNumber": "photo 35 - 473349183 - ssParade09-a20 - ELIZABETH ROBERTSON / Staff Photographer",
            "emailThis": "http://www.philly.com/philly/super-bowl-lii/fans-gather-to-celebrate-super-bowl-victory-at-eagles-parade-20180208.html#photoNumber=34",
            "photoWidth": "2048",
            "photoHeight": "1364",
            "reprint": "true",
            "_name": "http://media.philly.com/images/600*450/ssParade09-a20.JPG"
         },
         {
            "caption": "Philadelphia Eagles fans cheer across from the Philadelphia Art Museum many hours before the start of the Super Bowl Champions parade in Philadelphia on Thursday, February 8, 2018.",
            "title": "ssParade01-a2",
            "photoCredit": "DAVID MAIALETTI / Staff Photographer",
            "slideNumber": "photo 36 - 473349183 - ssParade01-a2 - DAVID MAIALETTI / Staff Photographer",
            "emailThis": "http://www.philly.com/philly/super-bowl-lii/fans-gather-to-celebrate-super-bowl-victory-at-eagles-parade-20180208.html#photoNumber=35",
            "photoWidth": "2048",
            "photoHeight": "1364",
            "reprint": "true",
            "_name": "http://media.philly.com/images/600*450/ssParade01-a2.JPG"
         },
         {
            "caption": "Eagles fan Michael Rahn from West Chester, Pa., wearing his dog mask with a Chewbacca costume, hours before the start of the Eagles Super Bowl Champions parade on S. Broad St. on Thursday morning, February 8, 2018.",
            "title": "ssParade01-a3",
            "photoCredit": "JOSE F. MORENO / Staff Photographer",
            "slideNumber": "photo 37 - 473349183 - ssParade01-a3 - JOSE F. MORENO / Staff Photographer",
            "emailThis": "http://www.philly.com/philly/super-bowl-lii/fans-gather-to-celebrate-super-bowl-victory-at-eagles-parade-20180208.html#photoNumber=36",
            "photoWidth": "2048",
            "photoHeight": "1364",
            "reprint": "true",
            "_name": "http://media.philly.com/images/600*450/ssParade01-a3.JPG"
         },
         {
            "caption": "David Rivera of Philadelphia at his spot on the street across from city hall with his girlfriend, Nicole Sharkey covered by their blanket as they try to fight off the early morning chill as they wait for the Eagles victory parade on Thursday February 8, 2018.",
            "title": "ssParade01-a5",
            "photoCredit": "MICHAEL BRYANT / Staff Photographer",
            "slideNumber": "photo 38 - 473349183 - ssParade01-a5 - MICHAEL BRYANT / Staff Photographer",
            "emailThis": "http://www.philly.com/philly/super-bowl-lii/fans-gather-to-celebrate-super-bowl-victory-at-eagles-parade-20180208.html#photoNumber=37",
            "photoWidth": "2048",
            "photoHeight": "1364",
            "reprint": "true",
            "_name": "http://media.philly.com/images/600*450/ssParade01-a5.JPG"
         },
         {
            "caption": "Eagle fan Christine Williams of Levittown, PA near Philadelphia City Hall. She and her family arrived around 6:00 a.m., Thursday morning to stake out their spot along the parade route to cheer their Super Bowl Champion, Philadelphia Eagles.",
            "title": "ssParade01-a6",
            "photoCredit": "MICHAEL BRYANT / Staff Photographer",
            "slideNumber": "photo 39 - 473349183 - ssParade01-a6 - MICHAEL BRYANT / Staff Photographer",
            "emailThis": "http://www.philly.com/philly/super-bowl-lii/fans-gather-to-celebrate-super-bowl-victory-at-eagles-parade-20180208.html#photoNumber=38",
            "photoWidth": "2048",
            "photoHeight": "1364",
            "reprint": "true",
            "_name": "http://media.philly.com/images/600*450/ssParade01-a6.JPG"
         },
         {
            "caption": "Fans cross the Ben Franklin Bridge into Philadelphia before 8 a.m. on the morning of the Eagles' Super Bowl parade in Center City.",
            "title": "ssParade01-a14",
            "photoCredit": "TIM TAI / Staff Photographer",
            "slideNumber": "photo 40 - 473349183 - ssParade01-a14 - TIM TAI / Staff Photographer",
            "emailThis": "http://www.philly.com/philly/super-bowl-lii/fans-gather-to-celebrate-super-bowl-victory-at-eagles-parade-20180208.html#photoNumber=39",
            "photoWidth": "2048",
            "photoHeight": "1364",
            "reprint": "true",
            "_name": "http://media.philly.com/images/600*450/ssParade01-a14.JPG"
         },
         {
            "caption": "Philadelphia Eagle fans cross JFK Blvd at 15th Street on their way down to the Ben Franklin Parkway at 6:30 am Thursday February 8 2018 in anticipation of the Eagles, Super Bowl Champions parade.",
            "title": "ssParade01-a4",
            "photoCredit": "MICHAEL BRYANT / Staff Photographer",
            "slideNumber": "photo 41 - 473349183 - ssParade01-a4 - MICHAEL BRYANT / Staff Photographer",
            "emailThis": "http://www.philly.com/philly/super-bowl-lii/fans-gather-to-celebrate-super-bowl-victory-at-eagles-parade-20180208.html#photoNumber=40",
            "photoWidth": "2048",
            "photoHeight": "1364",
            "reprint": "true",
            "_name": "http://media.philly.com/images/600*450/ssParade01-a4.JPG"
         },
         {
            "caption": "Overhead view of S. Broad St. in Center City Philadelphia as the motorcade of Philadelphia Eagles makes its way north from S. Philadelphia in route to main platform in front of Philadelphia Art Museum. The city of Philadelphia and region came out to celebrate during the Super Bowl Champions parade on Thursday, February 8, 2018.",
            "title": "ssParade09-b2",
            "photoCredit": "DAVID SWANSON / Staff Photograph",
            "slideNumber": "photo 42 - 473349183 - ssParade09-b2 - DAVID SWANSON / Staff Photograph",
            "emailThis": "http://www.philly.com/philly/super-bowl-lii/fans-gather-to-celebrate-super-bowl-victory-at-eagles-parade-20180208.html#photoNumber=41",
            "photoWidth": "2048",
            "photoHeight": "1365",
            "reprint": "true",
            "_name": "http://media.philly.com/images/600*450/ssParade09-b2.JPG"
         },
         {
            "caption": "Fans sit atop a garbage truck near Love Park before the Eagles' Super Bowl parade on Thursday, Feb. 8, 2018.",
            "title": "ssParade09-b5",
            "photoCredit": "TIM TAI / Staff Photographer",
            "slideNumber": "photo 43 - 473349183 - ssParade09-b5 - TIM TAI / Staff Photographer",
            "emailThis": "http://www.philly.com/philly/super-bowl-lii/fans-gather-to-celebrate-super-bowl-victory-at-eagles-parade-20180208.html#photoNumber=42",
            "photoWidth": "2048",
            "photoHeight": "1365",
            "reprint": "true",
            "_name": "http://media.philly.com/images/600*450/ssParade09-b5.JPG"
         },
         {
            "caption": "Eagles fans climb atop a statue across from Philadelphia City Hall before the Eagles' Super Bowl parade on Thursday, Feb. 8, 2018.",
            "title": "ssParade09-b6",
            "photoCredit": "TIM TAI / Staff Photographer",
            "slideNumber": "photo 44 - 473349183 - ssParade09-b6 - TIM TAI / Staff Photographer",
            "emailThis": "http://www.philly.com/philly/super-bowl-lii/fans-gather-to-celebrate-super-bowl-victory-at-eagles-parade-20180208.html#photoNumber=43",
            "photoWidth": "2048",
            "photoHeight": "1365",
            "reprint": "true",
            "_name": "http://media.philly.com/images/600*450/ssParade09-b6.JPG"
         },
         {
            "caption": "Thousands walk west on Market street towards 30th street Station after the Eagles Parade, Thursday, Feb. 8, 2018.",
            "title": "ssParade09-b7",
            "photoCredit": "STEVEN M. FALK / Staff Photographer",
            "slideNumber": "photo 45 - 473349183 - ssParade09-b7 - STEVEN M. FALK / Staff Photographer",
            "emailThis": "http://www.philly.com/philly/super-bowl-lii/fans-gather-to-celebrate-super-bowl-victory-at-eagles-parade-20180208.html#photoNumber=44",
            "photoWidth": "2048",
            "photoHeight": "1071",
            "reprint": "true",
            "_name": "http://media.philly.com/images/600*450/ssParade09-b7.JPG"
         },
         {
            "caption": "Fans cheer before the Eagles' Super Bowl parade on Thursday, Feb. 8, 2018.",
            "title": "ssParade09-b8",
            "photoCredit": "TIM TAI / Staff Photographer",
            "slideNumber": "photo 46 - 473349183 - ssParade09-b8 - TIM TAI / Staff Photographer",
            "emailThis": "http://www.philly.com/philly/super-bowl-lii/fans-gather-to-celebrate-super-bowl-victory-at-eagles-parade-20180208.html#photoNumber=45",
            "photoWidth": "2048",
            "photoHeight": "1365",
            "reprint": "true",
            "_name": "http://media.philly.com/images/600*450/ssParade09-b8.JPG"
         },
         {
            "caption": "Max Farren of Tampa, who flew in this morning to see the parade, wears an Eagles cape before the Eagles' Super Bowl parade on Thursday, Feb. 8, 2018.",
            "title": "ssParade09-b9",
            "photoCredit": "TIM TAI / Staff Photographer",
            "slideNumber": "photo 47 - 473349183 - ssParade09-b9 - TIM TAI / Staff Photographer",
            "emailThis": "http://www.philly.com/philly/super-bowl-lii/fans-gather-to-celebrate-super-bowl-victory-at-eagles-parade-20180208.html#photoNumber=46",
            "photoWidth": "2048",
            "photoHeight": "1365",
            "reprint": "true",
            "_name": "http://media.philly.com/images/600*450/ssParade09-b9.JPG"
         },
         {
            "caption": "Eagles fans carries a child on his shoulders while walking through the crowd before the Eagles' Super Bowl parade on Thursday, Feb. 8, 2018.",
            "title": "ssParade09-b10",
            "photoCredit": "TIM TAI / Staff Photographer",
            "slideNumber": "photo 48 - 473349183 - ssParade09-b10 - TIM TAI / Staff Photographer",
            "emailThis": "http://www.philly.com/philly/super-bowl-lii/fans-gather-to-celebrate-super-bowl-victory-at-eagles-parade-20180208.html#photoNumber=47",
            "photoWidth": "2048",
            "photoHeight": "1365",
            "reprint": "true",
            "_name": "http://media.philly.com/images/600*450/ssParade09-b10.JPG"
         },
         {
            "caption": "Maggie Dooley, 11, of Northeast Philadelphia, sports a green wig as she awaits the motorcade of players during the Super Bowl Champions parade on Thursday.",
            "title": "ssParade09-b11",
            "photoCredit": "TIM TAI / Staff Photographer",
            "slideNumber": "photo 49 - 473349183 - ssParade09-b11 - TIM TAI / Staff Photographer",
            "emailThis": "http://www.philly.com/philly/super-bowl-lii/fans-gather-to-celebrate-super-bowl-victory-at-eagles-parade-20180208.html#photoNumber=48",
            "photoWidth": "2048",
            "photoHeight": "1365",
            "reprint": "true",
            "_name": "http://media.philly.com/images/600*450/ssParade09-b11.JPG"
         },
         {
            "caption": "Eagle fans decided to climb on top of one of the city garbage trucks that was parked at Broad and Arch to get a better look at the Eagle Super Bowl Parade on Thursday February 8, 2018.",
            "title": "PARADE09-r",
            "photoCredit": "MICHAEL BRYANT / Staff Photographer",
            "slideNumber": "photo 50 - 473349183 - PARADE09-r - MICHAEL BRYANT / Staff Photographer",
            "emailThis": "http://www.philly.com/philly/super-bowl-lii/fans-gather-to-celebrate-super-bowl-victory-at-eagles-parade-20180208.html#photoNumber=49",
            "photoWidth": "3000",
            "photoHeight": "2000",
            "reprint": "true",
            "_name": "http://media.philly.com/images/600*450/RS_galleryImages_x_20180208_PARADE09_r.jpg"
         },
         {
            "caption": "Member of the Eagles march down the steps of the Philadelphia Museum of Art during the Super Bowl LII victory celebration on Thursday, February 8, 2018.",
            "title": "PARADE09",
            "photoCredit": "YONG KIM / Staff Photographer",
            "slideNumber": "photo 51 - 473349183 - PARADE09 - YONG KIM / Staff Photographer",
            "emailThis": "http://www.philly.com/philly/super-bowl-lii/fans-gather-to-celebrate-super-bowl-victory-at-eagles-parade-20180208.html#photoNumber=50",
            "photoWidth": "2400",
            "photoHeight": "1857",
            "reprint": "true",
            "_name": "http://media.philly.com/images/600*450/RS_galleryImages_x_20180208_PARADE09_18.JPG"
         },
         {
            "caption": "Eagles president Don Smolenski (left) holds up the Lombardi Trophy as the Eagles Super Bowl victory parade passes City Hall February 8, 2018.",
            "title": "PASSES08-D",
            "photoCredit": "TOM GRALISH / Staff Photographer",
            "slideNumber": "photo 52 - 473349183 - PASSES08-D - TOM GRALISH / Staff Photographer",
            "emailThis": "http://www.philly.com/philly/super-bowl-lii/fans-gather-to-celebrate-super-bowl-victory-at-eagles-parade-20180208.html#photoNumber=51",
            "photoWidth": "3708",
            "photoHeight": "2472",
            "reprint": "true",
            "_name": "http://media.philly.com/images/600*450/RS_galleryImages_x_20180208_PARADE09_D_455185101.jpg"
         },
         {
            "caption": "Eagles strong safety Malcolm Jenkins holds the Lombardi Trophy on the steps of the Philadelphia Museum of Art during the Super Bowl LII victory celebration on Thursday, February 8, 2018.",
            "title": "PARADE09",
            "photoCredit": "YONG KIM / Staff Photographer",
            "slideNumber": "photo 53 - 473349183 - PARADE09 - YONG KIM / Staff Photographer",
            "emailThis": "http://www.philly.com/philly/super-bowl-lii/fans-gather-to-celebrate-super-bowl-victory-at-eagles-parade-20180208.html#photoNumber=52",
            "photoWidth": "2400",
            "photoHeight": "1955",
            "reprint": "true",
            "_name": "http://media.philly.com/images/600*450/RS_galleryImages_x_20180208_PARADE09_22.JPG"
         },
         {
            "caption": "Eagle fans wanting to get a better look at the Eagles Super Bowl Parade as it came around city hall on Thursday February 8, 2018, decided to climb atop the bus shelters on JFK Blvd , across from Dilworth Plaza. MICHAEL BRYANT / Staff Photographer",
            "title": "PARADE09-x",
            "photoCredit": "MICHAEL BRYANT / Staff Photographer",
            "slideNumber": "photo 54 - 473349183 - PARADE09-x - MICHAEL BRYANT / Staff Photographer",
            "emailThis": "http://www.philly.com/philly/super-bowl-lii/fans-gather-to-celebrate-super-bowl-victory-at-eagles-parade-20180208.html#photoNumber=53",
            "photoWidth": "3000",
            "photoHeight": "2000",
            "reprint": "true",
            "_name": "http://media.philly.com/images/600*450/RS_galleryImages_x_20180208_PARADE09_x.jpg"
         }
      ]
   }
}
